Workbook

Sheet 汇报摘要
B2: 港股 IPO 数据库自动采集 · 模型成本汇报（2026Q1）
B3: 推荐方案：DeepSeek Flash + 独立复核 + 空闲时段 · 质量优先于单纯最低价 · 约 ¥1 / 家写进 Excel
B5: 样本快照（2026-09-12）
B6: 项目 | C6: 数量
B7: 主板样本公司（工作簿行） | C7: 38
B8: 招股书 PDF / 切片已齐 | C8: 38
B9: 配发公告 JSON 已齐 | C9: 38
B10: 招股书 JSON 已齐 | C10: 25
B11: 招股书待抽取（本估算覆盖） | C11: 13
B12: 招股书 JSON 有、表未写（0 token） | C12: 1
B14: 推荐方案：单家全流程到 Excel（人民币）
B15: 步骤 | C15: 是否调用 Flash | D15: 空闲 ¥/家 | E15: 高峰 ¥/家 | F15: 说明
B16: find / download / prepare（下招股书、切片） | C16: 否 | D16: ='单价假设'!C20 | E16: ='单价假设'!C20 | F16: Python，不计 token
B17: allot 准备（下配发公告） | C17: 否 | D17: ='单价假设'!C20 | E17: ='单价假设'!C20 | F17: Python；Q1 已完成
B18: 招股书抽取 + 独立复核 | C18: 是 | D18: ='单价假设'!C32 | E18: ='单价假设'!D32 | F18: packet≈11 万 token + 检索；含复核
B19: 配发抽取 + 独立复核 | C19: 是 | D19: ='单价假设'!C33 | E19: ='单价假设'!D33 | F19: 公告全文≈1.8 万 token；Q1 已完成
B20: validate + write 写回 Excel | C20: 否 | D20: ='单价假设'!C20 | E20: ='单价假设'!C20 | F20: 闸门校验，只赋值不改样式
B21: 单家合计（推荐） | C21: 是 | D21: =D16+D17+D18+D19+D20 | E21: =E16+E17+E18+E19+E20 | F21: 空闲约 ¥1/家；高峰约翻倍。下载本身不加钱。
B23: 2026Q1 预算（按推荐方案 · 公式随「单价假设」变动）
B24: 口径 | C24: 家数 | D24: 空闲合计 | E24: 高峰合计 | F24: 备注
B25: 收尾：抽剩余 13 家招股书（配发已齐） | C25: =C11 | D25: =C25*'单价假设'!C32 | E25: =C25*'单价假设'!D32 | F25: 当前立刻要花的钱
B26: 写回已有 JSON（含 2706） | C26: =C10 | D26: 0 | E26: 0 | F26: validate + write，¥0
B27: 若 38 家全部按推荐方案重跑一遍（含配发） | C27: =C7 | D27: =C27*'单价假设'!C34 | E27: =C27*'单价假设'!D34 | F27: 对照：全量重跑，不是建议
B28: Q1 已发生（Gemini 抽取，非正式换算） | C28: =C10 | D28: =C28*'单价假设'!C42 | E28: =C28*'单价假设'!C42 | F28: 体感 ¥3–4/家；见「对照方案」
B30: 汇报用一句话
B31: 在保证质量（packet 切片 + Flash 抽取 + 独立复核 + 勾稽闸门）的前提下，一家公司从下载招股书到写入 Excel 的模型费用，空闲时段约为 1 元人民币；当前 Q1 剩余 13 家招股书抽取预算约 10 元。下载、切片、校验、写表不计 token。若改用 Pro、高峰时段、或在对话里让模型通读全文，单家会回到 2–4 元，与前期 Gemini 体感一致。
B35: 价格来源：DeepSeek 官方「模型 & 价格」（https://api-docs.deepseek.com/zh-cn/quick_start/pricing），deepseek-flash / DeepSeek-V4.1-Flash。空闲价为高峰一半。高峰=北京时间周一至周五 9:00–12:00、14:00–18:00。Token 量按 38 家现成 packet 的 cl100k 计数 + 工具循环工程估算，不是 API 账单原件；建议抽 2 家后用控制台实扣校正。
B38: 图例
B39: 黄底蓝字 = 可改假设（请到「单价假设」页改）
B40: 绿底 = 推荐方案 / 当前应收尾预算
B41: 黑字 = 公式（随假设自动重算）
B43: 打开方式
B44: 本文件用公式计算。用 Microsoft Excel 打开后会自动算出金额；若预览里看到的是公式而不是 ¥0.95，请在 Excel / WPS 中打开一次。本机构建时未安装 LibreOffice，故没有预计算缓存值。手算核对：推荐单家空闲 ¥0.95、13 家收尾 ¥9.54、38 家全量重跑 ¥36.07，与公式一致。

Sheet 单价假设
B2: 计价假设（黄底为输入；改这里，摘要/对照/明细全部重算）
B4: A. 官方 Flash 单价（元 / 百万 tokens）
B5: 项目 | C5: 空闲 | D5: 高峰 | E5: 来源
B6: 输入未命中 cache miss | C6: 1 | D6: 2 | E6: 官方中文价 deepseek-flash
B7: 输入命中 cache hit | C7: 0.02 | D7: 0.04 | E7: 同上
B8: 输出（含 thinking） | C8: 4 | D8: 8 | E8: Flash 默认思考模式
B10: 高峰时段：北京时间周一至周五 9:00–12:00、14:00–18:00；其余为空闲（含周末全天）。旧模型名 deepseek-v4-flash 仍可调用，按 Flash 价计费。
B13: B. 单家 token 工程量（推荐质量：抽取 + 独立复核）
B14: 回合 | C14: cache miss | D14: cache hit | E14: 输出
B15: 招股书抽取 | C15: 178200 | D15: 2127200 | E15: 55600
B16: 招股书复核 | C16: 156300 | D16: 1142400 | E16: 27800
B17: 配发抽取 | C17: 46200 | D17: 252100 | E17: 18800
B18: 配发复核 | C18: 43500 | D18: 165900 | E18: 10600
B20: 零成本步骤占位（下载/写表） | C20: 0
B22: C. 单家费用（公式 = miss×单价 + hit×单价 + out×单价）
B23: 回合 | C23: 空闲 ¥ | D23: 高峰 ¥
B24: =B15 | C24: =C15/1000000*$C$6+D15/1000000*$C$7+E15/1000000*$C$8 | D24: =C15/1000000*$D$6+D15/1000000*$D$7+E15/1000000*$D$8
B25: =B16 | C25: =C16/1000000*$C$6+D16/1000000*$C$7+E16/1000000*$C$8 | D25: =C16/1000000*$D$6+D16/1000000*$D$7+E16/1000000*$D$8
B26: =B17 | C26: =C17/1000000*$C$6+D17/1000000*$C$7+E17/1000000*$C$8 | D26: =C17/1000000*$D$6+D17/1000000*$D$7+E17/1000000*$D$8
B27: =B18 | C27: =C18/1000000*$C$6+D18/1000000*$C$7+E18/1000000*$C$8 | D27: =C18/1000000*$D$6+D18/1000000*$D$7+E18/1000000*$D$8
B29: 招股书小计（抽+核） | C29: =C24+C25 | D29: =D24+D25
B30: 配发小计（抽+核） | C30: =C26+C27 | D30: =D26+D27
B32: 推荐·招股书到表（无配发） | C32: =C29 | D32: =D29
B33: 推荐·配发到表 | C33: =C30 | D33: =D30
B34: 推荐·全流程单家 | C34: =C32+C33 | D34: =D32+D33
B36: D. 质量对照（同一 Flash 价，不同流程）
B37: 方案 | C37: 空闲 ¥/家 | D37: 高峰 ¥/家 | E37: 质量取舍
B38: 最低价：一次读 packet 出 JSON，无复核、关 thinking | C38: 0.52 | D38: 1.04 | E38: 不建议。佣金/年化/基石容易错，闸门失败还要重跑。
B39: 推荐：抽取 + 独立复核，开 thinking（本表主方案） | C39: =C34 | D39: =D34 | E39: 质量与价格的平衡点。勾稽闸门 + 第二双眼睛。
B40: 难公司 / 校验返工 | C40: 1.67 | D40: 3.35 | E40: 少数 ERROR 返工；不要让它变成默认。
B42: 前期 Gemini 体感单价（仅对照） | C42: 3.5 | D42: 用户体感 ¥3–4/家；agy + gemini-3.8-flash-high，单家 75–180 次 API 轮次
B44: Pro 空闲/高峰 相对 Flash 的倍率（官方价）
B45: Pro 输入未命中 空闲 | C45: 4.5
B46: Pro 输入命中 空闲 | C46: 0.15
B47: Pro 输出 空闲 | C47: 13.5
B48: Pro 输入未命中 高峰 | C48: 9
B49: Pro 输入命中 高峰 | C49: 0.3
B50: Pro 输出 高峰 | C50: 27
B52: 同一 token 量若改用 Pro | C52: =(C15+C16+C17+C18)/1000000*C45+(D15+D16+D17+D18)/1000000*C46+(E15+E16+E17+E18)/1000000*C47 | D52: =(C15+C16+C17+C18)/1000000*C48+(D15+D16+D17+D18)/1000000*C49+(E15+E16+E17+E18)/1000000*C50 | E52: 空闲 / 高峰 ¥/家

Sheet 对照方案
B2: 为什么选 Flash + 复核，而不是更便宜或更贵
B4: 方案 | C4: 模型 / 跑法 | D4: 单家空闲 | E4: 38 家空闲 | F4: 质量 | G4: 适用
B5: A 一次读完出 JSON | C5: Flash，无复核、关 thinking | D5: ='单价假设'!C38 | E5: =C5*'汇报摘要'!C7 | F5: 低：年化/佣金/基石易错 | G5: 仅试跑，不入库
B6: B 推荐（本项目） | C6: Flash 抽取+复核，空闲，Python 下载 | D6: ='单价假设'!C34 | E6: =C6*'汇报摘要'!C7 | F6: 高：闸门+第二双眼睛 | G6: 默认生产路径
B7: C Flash 高峰 | C7: 同 B，工作日 9–12 / 14–18 | D7: ='单价假设'!D34 | E7: =C7*'汇报摘要'!C7 | F7: 同 B | G7: 能避开高峰就避开
B8: D DeepSeek Pro 空闲 | C8: 同 token 量改 Pro | D8: ='单价假设'!C52 | E8: =C8*'汇报摘要'!C7 | F8: 略高，性价比差 | G8: 极难公司才考虑
B9: E 对话里从零代劳 | C9: Flash 但通读全文、多轮 debug | D9: 3 | E9: =C9*'汇报摘要'!C7 | F9: 不稳定，费用不可控 | G9: 禁止作为流程
B10: F 前期 Gemini 体感 | C10: agy + gemini-3.8-flash-high | D10: ='单价假设'!C42 | E10: =C10*'汇报摘要'!C7 | F10: 能抽，但轮次 75–180 | G10: 已弃用
B12: 当前 Q1 收尾（只抽剩余 13 家招股书）
B13: 推荐 Flash 空闲 | C13: ='汇报摘要'!D25
B14: 若高峰跑完这 13 家 | C14: ='汇报摘要'!E25
B15: 若按 Gemini 体感价抽这 13 家 | C15: ='汇报摘要'!C11*'单价假设'!C42
B17: 质量机制（推荐方案自带，不另计费）：（1）Python 按章节切片，模型只看 packet 而非 600 页全文；（2）独立复核子代理重核股份恒等式、三年资产负债、佣金口径、绿鞋、基石名单；（3）validate 闸门：M=R+S、M=Q+P、L=N+Q、L=O+M，资产=权益+负债，U≤T，引文必须能在原文命中；ERROR 不写表。关 thinking 能再省约 ¥0.4/家，但闸门失败重跑会把节省吃掉，故不作为汇报口径。

Sheet 待抽明细
B2: 剩余 13 家招股书抽取（packet 已在，不必重新下载）
B4: # | C4: 代码 | D4: 公司（工作簿名称） | E4: 行号 | F4: 空闲 ¥ | G4: 高峰 ¥
B5: 1 | C5: 6809.HK | D5: Montage Technology Co., Ltd. - H shares | E5: 19 | F5: ='单价假设'!C32 | G5: ='单价假设'!D32
B6: 2 | C6: 0600.HK | D6: Axera Semiconductor Co., Ltd. - H shares | E6: 20 | F6: ='单价假设'!C32 | G6: ='单价假设'!D32
B7: 3 | C7: 0470.HK | D7: WUXI LEAD INTELLIGENT EQUIPMENT CO., LTD. - H shares | E7: 22 | F7: ='单价假设'!C32 | G7: ='单价假设'!D32
B8: 4 | C8: 2692.HK | D8: Shenzhen Zhaowei Machinery & Electronics Co., Ltd. - H Shares | E8: 27 | F8: ='单价假设'!C32 | G8: ='单价假设'!D32
B9: 5 | C9: 3268.HK | D9: MeiG Smart Technology Co., Ltd. - H Shares | E9: 28 | F9: ='单价假设'!C32 | G9: ='单价假设'!D32
B10: 6 | C10: 1989.HK | D10: Delton Technology (Guangzhou) Inc. - H Shares | E10: 29 | F10: ='单价假设'!C32 | G10: ='单价假设'!D32
B11: 7 | C11: 2701.HK | D11: Nsing Technologies Inc. - H Shares | E11: 30 | F11: ='单价假设'!C32 | G11: ='单价假设'!D32
B12: 8 | C12: 3355.HK | D12: FS.COM Ltd. - H Shares | E12: 31 | F12: ='单价假设'!C32 | G12: ='单价假设'!D32
B13: 9 | C13: 2632.HK | D13: Jiangsu New Vision Automotive Electronics Co., Ltd. - H Shares | E13: 32 | F13: ='单价假设'!C32 | G13: ='单价假设'!D32
B14: 10 | C14: 1021.HK | D14: Guangdong Huayan Robotics Co., Ltd. - H Shares | E14: 34 | F14: ='单价假设'!C32 | G14: ='单价假设'!D32
B15: 11 | C15: 2726.HK | D15: Epiworld International Co., Ltd. - H Shares | E15: 36 | F15: ='单价假设'!C32 | G15: ='单价假设'!D32
B16: 12 | C16: 6636.HK | D16: Shandong Extreme Vision Technology Co., Ltd. - H Shares | E16: 37 | F16: ='单价假设'!C32 | G16: ='单价假设'!D32
B17: 13 | C17: 0664.HK | D17: Hangzhou Tongshifu Cultural and Creative (Group) Co., Ltd. | E17: 38 | F17: ='单价假设'!C32 | G17: ='单价假设'!D32
B18: 合计（13 家 · 招股书抽+核） | F18: =SUM(F5:F17) | G18: =SUM(G5:G17)
B20: 另：2706.HK JSON 已存在，write-ready 写回 ¥0，不列入上表。
B21: 操作：DSH 说「抽剩下的」或 hkipo-one-shot；每批 2 家，空闲时段，deepseek-flash。

Sheet 口径与方法
B2: 口径、方法与局限（汇报附录）
B4: 1. 费用覆盖什么
B5: 覆盖：DeepSeek Flash 在「招股书抽取 + 独立复核」以及「配发抽取 + 独立复核」中的 API token 费用。不覆盖：港交所下载流量、本机 CPU、人工抽查时间、Excel 许可证、DeepSeek 账号充值优惠/赠金。Q1 配发 38/38 已完成，收尾只需招股书抽取。
B10: 2. 官方价格（2026-09-12 抓取）
B11: https://api-docs.deepseek.com/zh-cn/quick_start/pricing deepseek-flash：空闲 未命中 1 元、命中 0.02 元、输出 4 元 / 百万 tokens；高峰为 2 / 0.04 / 8。高峰=北京时间周一至周五 9:00–12:00、14:00–18:00。产品价格可能调整，以官网为准。
B15: 3. Token 如何估
B16: 38 家 prospectus packet 用 tiktoken cl100k：中位 107,125、均值 108,189、最大 135,195 tokens。配发 packet 均值 18,011。JSON 产出约 3,105 / 1,258。Agent 循环按「前缀重放 → cache hit、新检索片段 → cache miss、thinking+工具调用 → 输出」累加。这是工程估算，不是控制台账单。DeepSeek 分词与 cl100k 可能差 ±10%。校正方法：用推荐流程空闲抽 2 家，把实扣填进「单价假设」黄格。
B22: 4. 前期为什么体感是 ¥3–4
B23: 日志显示当时模型是 gemini-3.8-flash-high（agy），不是 DeepSeek Flash；成功案例单家 stream 75–180 次（推荐流程约十几到三十次）。同一 token 量若改用 DeepSeek Pro 空闲，公式结果约 4 元/家，与体感重合。对话里从零代劳（读全文 jsonl≈42 万 token）也会到 3–4 元。故体感真实，但不是 Flash 空闲生产价。
B28: 5. 质量如何保证（不另加预算）
B29: 切片上限见 prospectus_pipeline/config.yaml（财务组 95k 字符等）。手册硬规则：金额基本单位、百分比小数、year-1 销售/利润才年化、AO/AP 佣金口径、AQ 不默认 15%、AY 当期新增、无基石填 NA。validate 不通过禁止 write。关 thinking 可再降到约 ¥0.52，但失败重跑会抵消节省，汇报采用含复核的 ¥1 中枢。
B34: 6. 不在本预算内
... B40: python3 prospectus_pipeline/auto_fill.py status DSH 对话：抽剩下的 / hkipo-one-shot（每批 2 家，deepseek-flash） python3 prospectus_pipeline/auto_fill.py write-ready 工作簿：HKIPO-MB2026Q1.xlsx
